{
  "metadata": {
    "source_file": "../../Passeriformes/Tyrannidae/Tyrannidae_Image_Listing.xlsx",
    "generated_at": "2025-09-26T23:21:33.351353",
    "group_key": "SP_0602",
    "total_rows": 3,
    "columns": [
      "Species_ID",
      "Slug",
      "Subspecies_ID",
      "Slide",
      "Cover",
      "Thumbnail_Filename",
      "Large_Filename",
      "Equipment",
      "Sex_Age",
      "Location",
      "Province",
      "Country",
      "Date",
      "Location_Date",
      "Threat_Status"
    ],
    "column_range": "B-P"
  },
  "data": [
    {
      "Species_ID": "SP_0602",
      "Slug": "MosquetaPicoCurvo",
      "Subspecies_ID": null,
      "Slide": null,
      "Cover": "Y",
      "Thumbnail_Filename": "A_MosquetaPicoCurvo_EcoPortalDePiedra_18Oct2017_600.jpg",
      "Large_Filename": "A_MosquetaPicoCurvo_EcoPortalDePiedra_18Oct2017_1200.jpg",
      "Equipment": "Canon EOS 7D Mk II + Canon 100-400 f/4:5-5.6 L IS II USM + Extender EF III 1.4x",
      "Sex_Age": null,
      "Location": "Ecoportal de Piedra, Palma Sola",
      "Province": "Jujuy",
      "Country": null,
      "Date": "18-10-2017",
      "Location_Date": "Ecoportal de Piedra, Palma Sola, Jujuy - 18-10-2017",
      "Threat_Status": null
    },
    {
      "Species_ID": "SP_0602",
      "Slug": "MosquetaPicoCurvo",
      "Subspecies_ID": null,
      "Slide": null,
      "Cover": null,
      "Thumbnail_Filename": "A_MosquetaPicoCurvo2_EcoPortalDePiedra_18Oct2017_600.jpg",
      "Large_Filename": "A_MosquetaPicoCurvo2_EcoPortalDePiedra_18Oct2017_1200.jpg",
      "Equipment": "Canon EOS 7D Mk II + Canon 100-400 f/4:5-5.6 L IS II USM + Extender EF III 1.4x",
      "Sex_Age": null,
      "Location": "Ecoportal de Piedra, Palma Sola",
      "Province": "Jujuy",
      "Country": null,
      "Date": "18-10-2017",
      "Location_Date": "Ecoportal de Piedra, Palma Sola, Jujuy - 18-10-2017",
      "Threat_Status": null
    },
    {
      "Species_ID": "SP_0602",
      "Slug": "MosquetaPicoCurvo",
      "Subspecies_ID": null,
      "Slide": "Y",
      "Cover": null,
      "Thumbnail_Filename": "MosquetaPicoCurvo_Calilegua_Jul2000_th.jpg",
      "Large_Filename": "MosquetaPicoCurvo_Calilegua_Jul2000.jpg",
      "Equipment": null,
      "Sex_Age": null,
      "Location": "P. N. Calilegua",
      "Province": "Jujuy",
      "Country": null,
      "Date": "7-2000",
      "Location_Date": "P. N. Calilegua, Jujuy - 7/2000",
      "Threat_Status": null
    }
  ]
}